niafaker/__init__.py
niafaker/data/addresses.json
niafaker/data/cities.json
niafaker/data/countries.json
niafaker/data/names.json
niafaker/generators/__init__.py
niafaker/generators/addresses.py
niafaker/generators/cities.py
niafaker/generators/countries.py
niafaker/generators/names.py
tests/__init__.py
tests/test_generators.py
niafaker-0.1.1.dist-info/METADATA
niafaker-0.1.1.dist-info/WHEEL
niafaker-0.1.1.dist-info/top_level.txt
niafaker-0.1.1.dist-info/RECORD
