Metadata-Version: 2.1
Name: niafaker
Version: 0.1.1
Summary: A Faker package localized for African data
Home-page: https://github.com/owgee/niafaker
Author: Owden Godson (OG)
Author-email: owdeng@gmail.com
Classifier: Programming Language :: Python :: 3
Classifier: License :: OSI Approved :: MIT License
Classifier: Operating System :: OS Independent
Requires-Python: >=3.6
Requires-Dist: setuptools
